OSProfile/__init__.py
osprofile-0.2.1.dist-info/AUTHORS
osprofile-0.2.1.dist-info/METADATA
osprofile-0.2.1.dist-info/WHEEL
osprofile-0.2.1.dist-info/pbr.json
osprofile-0.2.1.dist-info/top_level.txt
osprofile-0.2.1.dist-info/RECORD
