Metadata-Version: 2.1
Name: osprofile
Version: 0.2.1
Summary: awsome project created by pycman.
Home-page: http://example.com
Author: singein
Author-email: singein@outlook.com
License: MIT
Platform: UNKNOWN
Requires-Dist: pycman
